{
  "Associated_Data": {
    "application": {
      "encoder_ticks": 1
    },
    "processor": {
      "Leak_Enable": true,
      "Max_Axon_Delay": 0,
      "Max_Leak": 4,
      "Max_Synapse_Delay": 255,
      "Max_Threshold": 127,
      "Max_Weight": 127,
      "Min_Axon_Delay": 0,
      "Min_Leak": -1,
      "Min_Synapse_Delay": 0,
      "Min_Threshold": 0,
      "Min_Weight": -127
    }
  },
  "Edges": [
    {
      "from": 14,
      "to": 97,
      "values": [
        73.0,
        52.0
      ]
    },
    {
      "from": 15,
      "to": 5,
      "values": [
        79.0,
        244.0
      ]
    },
    {
      "from": 14,
      "to": 15,
      "values": [
        41.0,
        137.0
      ]
    },
    {
      "from": 6,
      "to": 15,
      "values": [
        69.0,
        249.0
      ]
    },
    {
      "from": 5,
      "to": 14,
      "values": [
        -36.0,
        166.0
      ]
    },
    {
      "from": 12,
      "to": 4,
      "values": [
        37.0,
        166.0
      ]
    },
    {
      "from": 6,
      "to": 14,
      "values": [
        101.0,
        212.0
      ]
    },
    {
      "from": 1,
      "to": 5,
      "values": [
        15.0,
        202.0
      ]
    },
    {
      "from": 12,
      "to": 6,
      "values": [
        35.0,
        91.0
      ]
    },
    {
      "from": 5,
      "to": 3,
      "values": [
        43.0,
        238.0
      ]
    },
    {
      "from": 14,
      "to": 1,
      "values": [
        82.0,
        216.0
      ]
    },
    {
      "from": 15,
      "to": 56,
      "values": [
        -82.0,
        49.0
      ]
    },
    {
      "from": 12,
      "to": 11,
      "values": [
        93.0,
        144.0
      ]
    },
    {
      "from": 6,
      "to": 79,
      "values": [
        -118.0,
        172.0
      ]
    },
    {
      "from": 3,
      "to": 14,
      "values": [
        28.0,
        78.0
      ]
    },
    {
      "from": 2,
      "to": 2,
      "values": [
        15.0,
        42.0
      ]
    },
    {
      "from": 0,
      "to": 4,
      "values": [
        28.0,
        230.0
      ]
    },
    {
      "from": 94,
      "to": 79,
      "values": [
        112.0,
        67.0
      ]
    },
    {
      "from": 4,
      "to": 11,
      "values": [
        -63.0,
        44.0
      ]
    },
    {
      "from": 79,
      "to": 82,
      "values": [
        -121.0,
        189.0
      ]
    },
    {
      "from": 5,
      "to": 2,
      "values": [
        32.0,
        39.0
      ]
    },
    {
      "from": 0,
      "to": 12,
      "values": [
        123.0,
        17.0
      ]
    }
  ],
  "Inputs": [
    0,
    1
  ],
  "Network_Values": [],
  "Nodes": [
    {
      "id": 0,
      "values": [
        78.0,
        -1.0,
        0.0
      ]
    },
    {
      "id": 6,
      "values": [
        5.0,
        2.0,
        0.0
      ]
    },
    {
      "id": 12,
      "values": [
        82.0,
        1.0,
        0.0
      ]
    },
    {
      "id": 97,
      "values": [
        116.0,
        -1.0,
        0.0
      ]
    },
    {
      "id": 11,
      "values": [
        106.0,
        0.0,
        0.0
      ]
    },
    {
      "id": 15,
      "values": [
        4.0,
        3.0,
        0.0
      ]
    },
    {
      "id": 3,
      "values": [
        0.0,
        0.0,
        0.0
      ]
    },
    {
      "id": 94,
      "values": [
        117.0,
        -1.0,
        0.0
      ]
    },
    {
      "id": 46,
      "values": [
        95.0,
        1.0,
        0.0
      ]
    },
    {
      "id": 14,
      "values": [
        47.0,
        -1.0,
        0.0
      ]
    },
    {
      "id": 82,
      "values": [
        19.0,
        1.0,
        0.0
      ]
    },
    {
      "id": 56,
      "values": [
        76.0,
        1.0,
        0.0
      ]
    },
    {
      "id": 96,
      "values": [
        118.0,
        4.0,
        0.0
      ]
    },
    {
      "id": 17,
      "values": [
        23.0,
        2.0,
        0.0
      ]
    },
    {
      "id": 79,
      "values": [
        13.0,
        1.0,
        0.0
      ]
    },
    {
      "id": 2,
      "values": [
        20.0,
        1.0,
        0.0
      ]
    },
    {
      "id": 4,
      "values": [
        34.0,
        4.0,
        0.0
      ]
    },
    {
      "id": 1,
      "values": [
        120.0,
        4.0,
        0.0
      ]
    },
    {
      "id": 5,
      "values": [
        11.0,
        1.0,
        0.0
      ]
    }
  ],
  "Outputs": [
    2,
    3,
    4,
    5
  ],
  "Properties": {
    "edge_properties": [
      {
        "index": 1,
        "max_value": 255.0,
        "min_value": 0.0,
        "name": "Delay",
        "size": 1,
        "type": 73
      },
      {
        "index": 0,
        "max_value": 127.0,
        "min_value": -127.0,
        "name": "Weight",
        "size": 1,
        "type": 73
      }
    ],
    "network_properties": [],
    "node_properties": [
      {
        "index": 2,
        "max_value": 0.0,
        "min_value": 0.0,
        "name": "Delay",
        "size": 1,
        "type": 73
      },
      {
        "index": 1,
        "max_value": 4.0,
        "min_value": -1.0,
        "name": "Leak",
        "size": 1,
        "type": 73
      },
      {
        "index": 0,
        "max_value": 127.0,
        "min_value": 0.0,
        "name": "Threshold",
        "size": 1,
        "type": 73
      }
    ]
  }
}